[
    {
        "equipo1": "Rusia",
        "equipo2": "Arabia Saudí",
        "fecha": "14-06-2018",
        "hora": "17:00",
        "grupo": "A",
        "donde": "Moscú (Luzhnikí)",
        "golesE1": 5,
        "golesE2": 0,
        "canales": "TeleCinco"
    },
    {
        "equipo1": "Egipto",
        "equipo2": "Uruguay",
        "fecha": "15-06-2018",
        "hora": "14:00",
        "grupo": "A",
        "donde": "Ekaterimburgo (Ekaterimburgo Arena)",
        "golesE1": 0,
        "golesE2": 1,
        "canales": "Cuatro"
    },
    {
        "equipo1": "Marruecos",
        "equipo2": "Irán",
        "fecha": "15-06-2018",
        "hora": "17:00",
        "grupo": "B",
        "donde": "San Petersburgo",
        "golesE1": 0,
        "golesE2": 1,
        "canales": "Cuatro"
    },
    {
        "equipo1": "Portugal",
        "equipo2": "España",
        "fecha": "15-06-2018",
        "hora": "20:00",
        "grupo": "B",
        "donde": "Sochi (Estadio Fisht)",
        "golesE1": 3,
        "golesE2": 3,
        "canales": "TeleCinco"
    },
    {
        "equipo1": "Francia",
        "equipo2": "Australia",
        "fecha": "16-06-2018",
        "hora": "12:00",
        "grupo": "C",
        "donde": "Kazán (Kazán Arena)",
        "golesE1": 2,
        "golesE2": 1,
        "canales": "Cuatro"
    },
    {
        "equipo1": "Argentina",
        "equipo2": "Islandia",
        "fecha": "16-06-2018",
        "hora": "15:00",
        "grupo": "D",
        "donde": "Moscú (Estadio del Spartak)",
        "golesE1": 1,
        "golesE2": 1,
        "canales": "Cuatro"
    },
    {
        "equipo1": "Perú",
        "equipo2": "Dinamarca",
        "fecha": "16-06-2018",
        "hora": "18:00",
        "grupo": "C",
        "donde": "Saransk (Mordovia Arena)",
        "golesE1": 0,
        "golesE2": 1,
        "canales": "Cuatro"
    },
    {
        "equipo1": "Croacia",
        "equipo2": "Nigeria",
        "fecha": "16-06-2018",
        "hora": "21:00",
        "grupo": "D",
        "donde": "Kaliningrado (Estadio Kaliningrado)",
        "golesE1": 2,
        "golesE2": 0,
        "canales": "TeleCinco"
    },
    {
        "equipo1": "Costa Rica",
        "equipo2": "Serbia",
        "fecha": "17-06-2018",
        "hora": "14:00",
        "grupo": "E",
        "donde": "Samara (Samara Arena)",
        "golesE1": 0,
        "golesE2": 1,
        "canales": "Cuatro"
    },
    {
        "equipo1": "Alemania",
        "equipo2": "México",
        "fecha": "17-06-2018",
        "hora": "17:00",
        "grupo": "F",
        "donde": "Moscú (Luzhnikí)",
        "golesE1": 0,
        "golesE2": 1,
        "canales": "Cuatro"
    },
    {
        "equipo1": "Brasil",
        "equipo2": "Suiza",
        "fecha": "17-06-2018",
        "hora": "20:00",
        "grupo": "E",
        "donde": "Rostov del Don (Rostov Arena)",
        "golesE1": 1,
        "golesE2": 1,
        "canales": "TeleCinco"
    },
    {
        "equipo1": "Suecia",
        "equipo2": "Corea del Sur",
        "fecha": "18-06-2018",
        "hora": "14:00",
        "grupo": "F",
        "donde": "Nizhni Nóvgorod (Est. Nizhni Nóvgorod)",
        "golesE1": 1,
        "golesE2": 0,
        "canales": "Cuatro"
    },
    {
        "equipo1": "Bélgica",
        "equipo2": "Panamá",
        "fecha": "18-06-2018",
        "hora": "17:00",
        "grupo": "G",
        "donde": "Sochi (Estadio Fisht)",
        "golesE1": 3,
        "golesE2": 0,
        "canales": "Cuatro"
    },
    {
        "equipo1": "Túnez",
        "equipo2": "Inglaterra",
        "fecha": "18-06-2018",
        "hora": "20:00",
        "grupo": "G",
        "donde": "Volgogrado (Volgogrado Arena)",
        "golesE1": 1,
        "golesE2": 2,
        "canales": "TeleCinco"
    },
    {
        "equipo1": "Colombia",
        "equipo2": "Japón",
        "fecha": "19-06-2018",
        "hora": "14:00",
        "grupo": "H",
        "donde": "Saransk (Mordovia Arena)",
        "golesE1": "",
        "golesE2": "",
        "canales": "Cuatro"
    },
    {
        "equipo1": "Polonia",
        "equipo2": "Senegal",
        "fecha": "19-06-2018",
        "hora": "17:00",
        "grupo": "H",
        "donde": "Moscú (Estadio del Spartak)",
        "golesE1": "",
        "golesE2": "",
        "canales": "Cuatro"
    },
    {
        "equipo1": "Rusia",
        "equipo2": "Egipto",
        "fecha": "19-06-2018",
        "hora": "20:00",
        "grupo": "A",
        "donde": "San Petersburgo (Est. San Petersburgo)",
        "golesE1": "",
        "golesE2": "",
        "canales": "TeleCinco"
    },
    {
        "equipo1": "Portugal",
        "equipo2": "Marruecos",
        "fecha": "20-06-2018",
        "hora": "14:00",
        "grupo": "B",
        "donde": "Moscú (Estadio Luzhnikí)",
        "golesE1": "",
        "golesE2": "",
        "canales": "Cuatro"
    },
    {
        "equipo1": "Uruguay",
        "equipo2": "Arabia Saudí",
        "fecha": "20-06-2018",
        "hora": "17:00",
        "grupo": "A",
        "donde": "Rostov del Don (Rostov Arena)",
        "golesE1": "",
        "golesE2": "",
        "canales": "Cuatro"
    },
    {
        "equipo1": "Irán",
        "equipo2": "España",
        "fecha": "20-06-2018",
        "hora": "20:00",
        "grupo": "B",
        "donde": "Kazán (Kazán Arena)",
        "golesE1": "",
        "golesE2": "",
        "canales": "TeleCinco"
    },
    {
        "equipo1": "Dinamarca",
        "equipo2": "Australia",
        "fecha": "21-06-2018",
        "hora": "14:00",
        "grupo": "C",
        "donde": "Samara (Samara Arena)",
        "golesE1": "",
        "golesE2": "",
        "canales": "Cuatro"
    },
    {
        "equipo1": "Francia",
        "equipo2": "Perú",
        "fecha": "21-06-2018",
        "hora": "17:00",
        "grupo": "C",
        "donde": "Ekaterimburgo (Ekaterimburgo Arena)",
        "golesE1": "",
        "golesE2": "",
        "canales": "Cuatro"
    },
    {
        "equipo1": "Argentina",
        "equipo2": "Croacia",
        "fecha": "21-06-2018",
        "hora": "20:00",
        "grupo": "D",
        "donde": "Nizhni Nóvgorod (Est. Nizhni Nóvgorod)",
        "golesE1": "",
        "golesE2": "",
        "canales": "TeleCinco"
    },
    {
        "equipo1": "Brasil",
        "equipo2": "Costa Rica",
        "fecha": "22-06-2018",
        "hora": "14:00",
        "grupo": "E",
        "donde": "San Petersburgo (Est. San Petersburgo)",
        "golesE1": "",
        "golesE2": "",
        "canales": "Cuatro"
    },
    {
        "equipo1": "Nigeria",
        "equipo2": "Islandia",
        "fecha": "22-06-2018",
        "hora": "17:00",
        "grupo": "D",
        "donde": "Volgogrado (Volgogrado Arena)",
        "golesE1": "",
        "golesE2": "",
        "canales": "Cuatro"
    },
    {
        "equipo1": "Serbia",
        "equipo2": "Suiza",
        "fecha": "22-06-2018",
        "hora": "20:00",
        "grupo": "E",
        "donde": "Kaliningrado (Estadio Kaliningrado)",
        "golesE1": "",
        "golesE2": "",
        "canales": "TeleCinco"
    },
    {
        "equipo1": "Bélgica",
        "equipo2": "Túnez",
        "fecha": "23-06-2018",
        "hora": "14:00",
        "grupo": "G",
        "donde": "Moscú (Estadio del Spartak)",
        "golesE1": "",
        "golesE2": "",
        "canales": "Cuatro"
    },
    {
        "equipo1": "Corea del Sur",
        "equipo2": "México",
        "fecha": "23-06-2018",
        "hora": "17:00",
        "grupo": "F",
        "donde": "Rostov del Don (Rostov Arena)",
        "golesE1": "",
        "golesE2": "",
        "canales": "Cuatro"
    },
    {
        "equipo1": "Alemania",
        "equipo2": "Suecia",
        "fecha": "23-06-2018",
        "hora": "20:00",
        "grupo": "F",
        "donde": "Sochi (Estadio Fisht)",
        "golesE1": "",
        "golesE2": "",
        "canales": "TeleCinco"
    },
    {
        "equipo1": "Inglaterra",
        "equipo2": "Panamá",
        "fecha": "24-06-2018",
        "hora": "14:00",
        "grupo": "G",
        "donde": "Nizhni Nóvgorod (Est. Nizhni Nóvgorod)",
        "golesE1": "",
        "golesE2": "",
        "canales": "Cuatro"
    },
    {
        "equipo1": "Japón",
        "equipo2": "Senegal",
        "fecha": "24-06-2018",
        "hora": "17:00",
        "grupo": "H",
        "donde": "Ekaterimburgo (Ekaterimburgo Arena)",
        "golesE1": "",
        "golesE2": "",
        "canales": "Cuatro"
    },
    {
        "equipo1": "Polonia",
        "equipo2": "Colombia",
        "fecha": "24-06-2018",
        "hora": "20:00",
        "grupo": "H",
        "donde": "Kazán (Kazán Arena)",
        "golesE1": "",
        "golesE2": "",
        "canales": "TeleCinco"
    },
    {
        "equipo1": "Uruguay",
        "equipo2": "Rusia",
        "fecha": "25-06-2018",
        "hora": "16:00",
        "grupo": "A",
        "donde": "Samara (Samara Arena)",
        "golesE1": "",
        "golesE2": "",
        "canales": "Cuatro*, BE MAD*"
    },
    {
        "equipo1": "Arabia Saudí",
        "equipo2": "Egipto",
        "fecha": "25-06-2018",
        "hora": "16:00",
        "grupo": "A",
        "donde": "Volgogrado (Volgogrado Arena)",
        "golesE1": "",
        "golesE2": "",
        "canales": "Cuatro*, BE MAD*"
    },
    {
        "equipo1": "Irán",
        "equipo2": "Portugal",
        "fecha": "25-06-2018",
        "hora": "20:00",
        "grupo": "B",
        "donde": "Saransk (Mordovia Arena)",
        "golesE1": "",
        "golesE2": "",
        "canales": "Cuatro*, BE MAD*"
    },
    {
        "equipo1": "España",
        "equipo2": "Marruecos",
        "fecha": "25-06-2018",
        "hora": "20:00",
        "grupo": "B",
        "donde": "Kaliningrado (Estadio Kaliningrado)",
        "golesE1": "",
        "golesE2": "",
        "canales": "TeleCinco"
    },
    {
        "equipo1": "Dinamarca",
        "equipo2": "Francia",
        "fecha": "26-06-2018",
        "hora": "16:00",
        "grupo": "C",
        "donde": "Moscú (Estadio Luzhnikí)",
        "golesE1": "",
        "golesE2": "",
        "canales": "Cuatro*, BE MAD*"
    },
    {
        "equipo1": "Australia",
        "equipo2": "Perú",
        "fecha": "26-06-2018",
        "hora": "16:00",
        "grupo": "C",
        "donde": "Sochi (Estadio Fisht)",
        "golesE1": "",
        "golesE2": "",
        "canales": "Cuatro*, BE MAD*"
    },
    {
        "equipo1": "Islandia",
        "equipo2": "Croacia",
        "fecha": "26-06-2018",
        "hora": "20:00",
        "grupo": "D",
        "donde": "Rostov del Don (Rostov Arena)",
        "golesE1": "",
        "golesE2": "",
        "canales": "Cuatro*, BE MAD*"
    },
    {
        "equipo1": "Nigeria",
        "equipo2": "Argentina",
        "fecha": "26-06-2018",
        "hora": "20:00",
        "grupo": "D",
        "donde": "San Petersburgo (Est. San Petersburgo)",
        "golesE1": "",
        "golesE2": "",
        "canales": "TeleCinco"
    },
    {
        "equipo1": "Corea del Sur",
        "equipo2": "Alemania",
        "fecha": "27-06-2018",
        "hora": "16:00",
        "grupo": "F",
        "donde": "Kazán (Kazán Arena)",
        "golesE1": "",
        "golesE2": "",
        "canales": "Cuatro*, BE MAD*"
    },
    {
        "equipo1": "México",
        "equipo2": "Suecia",
        "fecha": "27-06-2018",
        "hora": "16:00",
        "grupo": "F",
        "donde": "Ekaterimburgo (Ekaterimburgo Arena)",
        "golesE1": "",
        "golesE2": "",
        "canales": "Cuatro*, BE MAD*"
    },
    {
        "equipo1": "Serbia",
        "equipo2": "Brasil",
        "fecha": "27-06-2018",
        "hora": "20:00",
        "grupo": "E",
        "donde": "Moscú (Estadio del Spartak)",
        "golesE1": "",
        "golesE2": "",
        "canales": "TeleCinco"
    },
    {
        "equipo1": "Suiza",
        "equipo2": "Costa Rica",
        "fecha": "27-06-2018",
        "hora": "20:00",
        "grupo": "E",
        "donde": "Nizhni Nóvgorod (Est. Nizhni Nóvgorod)",
        "golesE1": "",
        "golesE2": "",
        "canales": "Cuatro*, BE MAD*"
    },
    {
        "equipo1": "Japón",
        "equipo2": "Polonia",
        "fecha": "28-06-2018",
        "hora": "16:00",
        "grupo": "H",
        "donde": "Volgogrado (Volgogrado Arena)",
        "golesE1": "",
        "golesE2": "",
        "canales": "Cuatro*, BE MAD*"
    },
    {
        "equipo1": "Senegal",
        "equipo2": "Colombia",
        "fecha": "28-06-2018",
        "hora": "16:00",
        "grupo": "H",
        "donde": "Samara (Samara Arena)",
        "golesE1": "",
        "golesE2": "",
        "canales": "Cuatro*, BE MAD*"
    },
    {
        "equipo1": "Inglaterra",
        "equipo2": "Bélgica",
        "fecha": "28-06-2018",
        "hora": "20:00",
        "grupo": "G",
        "donde": "Kaliningrado (Estadio Kaliningrado)",
        "golesE1": "",
        "golesE2": "",
        "canales": "TeleCinco"
    },
    {
        "equipo1": "Panamá",
        "equipo2": "Túnez",
        "fecha": "28-06-2018",
        "hora": "20:00",
        "grupo": "G",
        "donde": "Saransk (Mordovia Arena)",
        "golesE1": "",
        "golesE2": "",
        "canales": "Cuatro*, BE MAD*"
    },
    {
        "equipo1": "1º Grupo C",
        "equipo2": "2º Grupo D",
        "fecha": "30-06-2018",
        "hora": "16:00",
        "grupo": "Octavos",
        "donde": "Kazán (Kazán Arena)",
        "golesE1": "",
        "golesE2": "",
        "canales": "Cuatro"
    },
    {
        "equipo1": "1º Grupo A",
        "equipo2": "2º Grupo B",
        "fecha": "30-06-2018",
        "hora": "20:00",
        "grupo": "Octavos",
        "donde": "Sochi (Estadio Fisht)",
        "golesE1": "",
        "golesE2": "",
        "canales": "TeleCinco"
    },
    {
        "equipo1": "1º Grupo B",
        "equipo2": "2º Grupo A",
        "fecha": "01-07-2018",
        "hora": "16:00",
        "grupo": "Octavos",
        "donde": "Moscú (Estadio Luzhnikí)",
        "golesE1": "",
        "golesE2": "",
        "canales": "Cuatro"
    },
    {
        "equipo1": "1º Grupo D",
        "equipo2": "2º Grupo C",
        "fecha": "01-07-2018",
        "hora": "20:00",
        "grupo": "Octavos",
        "donde": "Nizhni Nóvgorod (Est. Nizhni Nóvgorod)",
        "golesE1": "",
        "golesE2": "",
        "canales": "TeleCinco"
    },
    {
        "equipo1": "1º Grupo E",
        "equipo2": "2º Grupo F",
        "fecha": "02-07-2018",
        "hora": "16:00",
        "grupo": "Octavos",
        "donde": "Samara (Samara Arena)",
        "golesE1": "",
        "golesE2": "",
        "canales": "Cuatro*, TeleCinco*"
    },
    {
        "equipo1": "1º Grupo G",
        "equipo2": "2º Grupo H",
        "fecha": "02-07-2018",
        "hora": "20:00",
        "grupo": "Octavos",
        "donde": "Rostov del Don (Rostov Arena)",
        "golesE1": "",
        "golesE2": "",
        "canales": "TeleCinco"
    },
    {
        "equipo1": "1º Grupo F",
        "equipo2": "2º Grupo E",
        "fecha": "03-07-2018",
        "hora": "16:00",
        "grupo": "Octavos",
        "donde": "San Petersburgo (Est. San Petersburgo)",
        "golesE1": "",
        "golesE2": "",
        "canales": "Cuatro"
    },
    {
        "equipo1": "1º Grupo H",
        "equipo2": "2º Grupo G",
        "fecha": "03-07-2018",
        "hora": "20:00",
        "grupo": "Octavos",
        "donde": "Moscú (Estadio del Spartak)",
        "golesE1": "",
        "golesE2": "",
        "canales": "TeleCinco"
    },
    {
        "equipo1": "Ganador Partido 49",
        "equipo2": "Ganador Partido 50",
        "fecha": "06-07-2018",
        "hora": "16:00",
        "grupo": "Cuartos",
        "donde": "Nizhni Nóvgorod (Est. Nizhni Nóvgorod)",
        "golesE1": "",
        "golesE2": "",
        "canales": "Cuatro"
    },
    {
        "equipo1": "Ganador Partido 53",
        "equipo2": "Ganador Partido 54",
        "fecha": "06-07-2018",
        "hora": "20:00",
        "grupo": "Cuartos",
        "donde": "Kazán (Kazán Arena)",
        "golesE1": "",
        "golesE2": "",
        "canales": "TeleCinco"
    },
    {
        "equipo1": "Ganador Partido 55",
        "equipo2": "Ganador Partido 56",
        "fecha": "07-07-2018",
        "hora": "16:00",
        "grupo": "Cuartos",
        "donde": "Samara (Samara Arena)",
        "golesE1": "",
        "golesE2": "",
        "canales": "Cuatro"
    },
    {
        "equipo1": "Ganador Partido 51",
        "equipo2": "Ganador Partido 52",
        "fecha": "07-07-2018",
        "hora": "20:00",
        "grupo": "Cuartos",
        "donde": "Sochi (Estadio Fisht)",
        "golesE1": "",
        "golesE2": "",
        "canales": "TeleCinco"
    },
    {
        "equipo1": "Ganador Partido 57",
        "equipo2": "Ganador Partido 58",
        "fecha": "10-07-2018",
        "hora": "20:00",
        "grupo": "Semifinal",
        "donde": "San Petersburgo (Est. San Petersburgo)",
        "golesE1": "",
        "golesE2": "",
        "canales": "TeleCinco"
    },
    {
        "equipo1": "Ganador Partido 59",
        "equipo2": "Ganador Partido 60",
        "fecha": "11-07-2018",
        "hora": "20:00",
        "grupo": "Semifinal",
        "donde": "Moscú (Estadio Luzhnikí)",
        "golesE1": "",
        "golesE2": "",
        "canales": "TeleCinco"
    },
    {
        "equipo1": "Perdedor Partido 61",
        "equipo2": "Perdedor Partido 62",
        "fecha": "14-07-2018",
        "hora": "16:00",
        "grupo": "3º/4º Puesto",
        "donde": "San Petersburgo (Est. San Petersburgo)",
        "golesE1": "",
        "golesE2": "",
        "canales": "TeleCinco"
    },
    {
        "equipo1": "Ganador Partido 61",
        "equipo2": "Ganador Partido 62",
        "fecha": "15-07-2018",
        "hora": "17:00",
        "grupo": "Final",
        "donde": "Moscú (Estadio Luzhnikí)",
        "golesE1": "",
        "golesE2": "",
        "canales": "TeleCinco"
    }
]